gabel/__init__.py
gabel/_gabel.py
gabel-0.0.1.dist-info/METADATA
gabel-0.0.1.dist-info/WHEEL
gabel-0.0.1.dist-info/top_level.txt
gabel-0.0.1.dist-info/RECORD
