Metadata-Version: 2.1
Name: gabel
Version: 0.0.1
Summary: I dont know why you whould you ever install this thing
Home-page: UNKNOWN
Author: Will Gabel
License: no one
Keywords: gabel
Platform: UNKNOWN
Requires-Python: >= 3.5
